dstk/__init__.py
dstk_x250-4.0.0.dist-info/licenses/LICENSE.txt
dstk_x250-4.0.0.dist-info/METADATA
dstk_x250-4.0.0.dist-info/WHEEL
dstk_x250-4.0.0.dist-info/top_level.txt
dstk_x250-4.0.0.dist-info/RECORD
