Metadata-Version: 2.4
Name: dstk_x250
Version: 4.0.0
Summary: Package d'utilitaires pour les projets de data science.
Author-email: Cyrile Delestre <cyrile.ufr.orsay@gmail.com>
License: Apache-2.0
Requires-Python: >=3.5
License-File: LICENSE.txt
Requires-Dist: joblib
Requires-Dist: numpy
Requires-Dist: scikit-learn>=1.1.1
Requires-Dist: pandas
Requires-Dist: tqdm
Dynamic: license-file
